stepup/queue/__init__.py
stepup/queue/actions.py
stepup/queue/api.py
stepup/queue/canceljobs.py
stepup/queue/removejobs.py
stepup/queue/sbatch.py
stepup/queue/utils.py
stepup_queue-1.1.0.dist-info/licenses/LICENSE
stepup_queue-1.1.0.dist-info/METADATA
stepup_queue-1.1.0.dist-info/WHEEL
stepup_queue-1.1.0.dist-info/entry_points.txt
stepup_queue-1.1.0.dist-info/top_level.txt
stepup_queue-1.1.0.dist-info/RECORD
