Metadata-Version: 2.4
Name: stepup-queue
Version: 1.1.0
Summary: StepUp Queue integrates queued jobs into a StepUp workflow.
Author-email: Toon Verstraelen <toon.verstraelen@ugent.be>
License-Expression: GPL-3.0-or-later
Project-URL: Documentation, https://reproducible-reporting.github.io/stepup-queue/
Project-URL: Issues, https://github.com/reproducible-reporting/stepup-queue/issues
Project-URL: Source, https://github.com/reproducible-reporting/stepup-queue/
Project-URL: Changelog, https://reproducible-reporting.github.io/stepup-queue/changelog/
Classifier: Development Status :: 4 - Beta
Classifier: Environment :: Console
Classifier: Intended Audience :: Education
Classifier: Intended Audience :: Science/Research
Classifier: Natural Language :: English
Classifier: Operating System :: POSIX
Classifier: Operating System :: MacOS
Classifier: Programming Language :: Python :: 3
Classifier: Programming Language :: Python :: 3.11
Classifier: Programming Language :: Python :: 3.12
Classifier: Programming Language :: Python :: 3.13
Classifier: Programming Language :: Python :: 3.14
Classifier: Topic :: Software Development :: Build Tools
Requires-Python: >=3.11
License-File: LICENSE
Requires-Dist: path>=16.14.0
Requires-Dist: stepup<4.0.0,>=3.2.0
Provides-Extra: dev
Requires-Dist: psutil; extra == "dev"
Requires-Dist: pytest; extra == "dev"
Requires-Dist: pytest-asyncio>=0.24; extra == "dev"
Requires-Dist: pytest-xdist; extra == "dev"
Requires-Dist: mike; extra == "dev"
Requires-Dist: mkdocs; extra == "dev"
Requires-Dist: mkdocstrings[python]; extra == "dev"
Requires-Dist: mkdocs-macros-plugin; extra == "dev"
Requires-Dist: mkdocs-material; extra == "dev"
Dynamic: license-file
